<?xml version="1.0" encoding="utf-8" ?>
<dwsync>
<file name="2.jpg" server="ftp.scribblehack.com" local="130354470746277802" remote="130366812000000000" Dst="1" />
<file name="arrow.gif" server="ftp.scribblehack.com" local="130354470749267973" remote="130366812000000000" Dst="1" />
<file name="art1.png" server="ftp.scribblehack.com" local="130354470749317976" remote="130366812000000000" Dst="1" />
<file name="art2.png" server="ftp.scribblehack.com" local="130354470754308261" remote="130366812000000000" Dst="1" />
<file name="avatar1.png" server="ftp.scribblehack.com" local="130354470754318262" remote="130366812000000000" Dst="1" />
<file name="bannerbrowse.jpg" server="ftp.scribblehack.com" local="130354470757878465" remote="130366812000000000" Dst="1" />
<file name="bookshelf.jpg" server="ftp.scribblehack.com" local="130354470763198769" remote="130366812000000000" Dst="1" />
<file name="bottle1.jpg" server="ftp.scribblehack.com" local="130354470763908810" remote="130366812000000000" Dst="1" />
<file name="bi.jpg" server="ftp.scribblehack.com" local="130354470767088992" remote="130366812000000000" Dst="1" />
<file name="browsebanner.jpg" server="ftp.scribblehack.com" local="130354470769369122" remote="130366812000000000" Dst="1" />
<file name="bottle_and_message.jpg" server="ftp.scribblehack.com" local="130354470776509531" remote="130366812000000000" Dst="1" />
<file name="clipboard.jpg" server="ftp.scribblehack.com" local="130354470777289575" remote="130366812000000000" Dst="1" />
<file name="clipboardbutton.jpg" server="ftp.scribblehack.com" local="130354470781239801" remote="130366812000000000" Dst="1" />
<file name="clipboard.png" server="ftp.scribblehack.com" local="130354470786990130" remote="130366812000000000" Dst="1" />
<file name="clipboard2.jpg" server="ftp.scribblehack.com" local="130354470792660455" remote="130366812000000000" Dst="1" />
<file name="coverart.jpg" server="ftp.scribblehack.com" local="130354470792670455" remote="130366812000000000" Dst="1" />
<file name="heart.png" server="ftp.scribblehack.com" local="130354470796490674" remote="130366812000000000" Dst="1" />
<file name="like_button.png" server="ftp.scribblehack.com" local="130354470799190828" remote="130366812000000000" Dst="1" />
<file name="likeicon.png" server="ftp.scribblehack.com" local="130354470801570964" remote="130366812000000000" Dst="1" />
<file name="logbox.png" server="ftp.scribblehack.com" local="130354470807611310" remote="130366812000000000" Dst="1" />
<file name="content.jpg" server="ftp.scribblehack.com" local="130354470809911441" remote="130366812000000000" Dst="1" />
<file name="gallery.jpg" server="ftp.scribblehack.com" local="130354470812151569" remote="130366812000000000" Dst="1" />
<file name="logo.png" server="ftp.scribblehack.com" local="130354470812171571" remote="130366812000000000" Dst="1" />
<file name="login.png" server="ftp.scribblehack.com" local="130354470815861782" remote="130366812000000000" Dst="1" />
<file name="mermaid_1.jpg" server="ftp.scribblehack.com" local="130354470818061907" remote="130366812000000000" Dst="1" />
<file name="mermaid_2.jpg" server="ftp.scribblehack.com" local="130354470820282034" remote="130366812000000000" Dst="1" />
<file name="logobig.png" server="ftp.scribblehack.com" local="130354470820782063" remote="130366812000000000" Dst="1" />
<file name="mermaid_3.jpg" server="ftp.scribblehack.com" local="130354470824382269" remote="130366812000000000" Dst="1" />
<file name="navbarsearchbox.jpg" server="ftp.scribblehack.com" local="130354470824402270" remote="130366812000000000" Dst="1" />
<file name="message1.jpg" server="ftp.scribblehack.com" local="130354470828182486" remote="130366812000000000" Dst="1" />
<file name="refresh.png" server="ftp.scribblehack.com" local="130354470831022649" remote="130366812000000000" Dst="1" />
<file name="octobanner.jpg" server="ftp.scribblehack.com" local="130354470831102653" remote="130366812000000000" Dst="1" />
<file name="profilepic.jpg" server="ftp.scribblehack.com" local="130354470834642856" remote="130366812000000000" Dst="1" />
<file name="searchicon.png" server="ftp.scribblehack.com" local="130354470834642856" remote="130366812000000000" Dst="1" />
<file name="showmore.png" server="ftp.scribblehack.com" local="130354470834752862" remote="130366812000000000" Dst="1" />
<file name="testimage1.jpg" server="ftp.scribblehack.com" local="130354470842783321" remote="130366812600000000" Dst="1" />
<file name="slider.jpg" server="ftp.scribblehack.com" local="130354470843393356" remote="130366812600000000" Dst="1" />
<file name="testimage3.jpg" server="ftp.scribblehack.com" local="130354470847253577" remote="130366812600000000" Dst="1" />
<file name="testimage2.jpg" server="ftp.scribblehack.com" local="130354470847753606" remote="130366812600000000" Dst="1" />
<file name="testimage4.jpg" server="ftp.scribblehack.com" local="130354470851423816" remote="130366812600000000" Dst="1" />
<file name="testimage5.jpg" server="ftp.scribblehack.com" local="130354470855114027" remote="130366812600000000" Dst="1" />
<file name="testimage6.jpg" server="ftp.scribblehack.com" local="130354470857464161" remote="130366812600000000" Dst="1" />
<file name="users1.png" server="ftp.scribblehack.com" local="130354470857524165" remote="130366812600000000" Dst="1" />
<file name="users2.png" server="ftp.scribblehack.com" local="130354470861144372" remote="130366812600000000" Dst="1" />
<file name="testimage7.jpg" server="ftp.scribblehack.com" local="130354470863444503" remote="130366812600000000" Dst="1" />
<file name="writing1.png" server="ftp.scribblehack.com" local="130354470863584511" remote="130366812600000000" Dst="1" />
<file name="writing2.png" server="ftp.scribblehack.com" local="130354470867854755" remote="130366812600000000" Dst="1" />
<file name="wrapperbg.jpg" server="ftp.scribblehack.com" local="130354470885575769" remote="130366812600000000" Dst="1" />
<file name="congratsbanner.jpg" server="ftp.scribblehack.com" local="130366421967406952" remote="130366812000000000" Dst="1" />
<file name="narwhal.png" server="ftp.scribblehack.com" local="130366421967526959" remote="130366812000000000" Dst="1" />
<file name="logo3.png" server="ftp.scribblehack.com" local="130284502580000000" remote="130366812000000000" Dst="1" />
<file name="logonavbg.png" server="ftp.scribblehack.com" local="130272767700000000" remote="130366812000000000" Dst="1" />
</dwsync>